pyclo/__init__.py
pyclo/test_init.py
pyclo-0.1.0.dist-info/METADATA
pyclo-0.1.0.dist-info/WHEEL
pyclo-0.1.0.dist-info/top_level.txt
pyclo-0.1.0.dist-info/RECORD
