Metadata-Version: 2.1
Name: pyclo
Version: 0.1.0
Summary: Immutable manipulation of Python data structures, Clojure style
Home-page: https://github.com/pb-/pyclo
Author: Paul Baecher
License: UNKNOWN
Platform: UNKNOWN
Classifier: Programming Language :: Python :: 3
Classifier: License :: OSI Approved :: MIT License
Classifier: Operating System :: OS Independent
